Workbook

Sheet README
B2: Northwind Cloud — unit economics and runway model
B3: Board question: does the current sales machine pay back, and should we add $180k/month of SDR capacity?
B6: HOW TO USE
B7: 1. | C7: Open CONTROL and pick a scenario in the blue cell B3. Every downstream number moves.
B8: 2. | C8: All other blue cells on CONTROL are live assumptions. Change one and the model recalculates.
B9: 3. | C9: CHECKS reconciles this workbook against the SQL warehouse. Every row must read PASS.
B11: COLOUR CONVENTION
B12: Blue | C12: Hard input. The only cells a user should type into.
B13: Black | C13: Formula computed on this sheet.
B14: Green | C14: Formula referencing another sheet.
B16: SHEETS
B17: CONTROL | C17: Scenario switch and every assumption the model uses.
B18: DATA_ACTUALS | C18: 36 months of actuals from the warehouse. Input only.
B19: DATA_CHANNELS | C19: Trailing-12-month cost pools and behaviour by channel.
B20: DATA_SEGMENTS | C20: Segment margins, retention, outbound ACV, sales-cycle lag.
B21: DATA_SCENARIOS | C21: The three scenarios, one column each.
B22: DATA_SQL_CHECK | C22: Reference values produced by the SQL library and the Python cash model, used by CHECKS.
B23: CALC_UNIT_ECON | C23: CAC, LTV and payback by channel — all formulas.
B24: CALC_FORECAST | C24: Holt recursion, SDR saturation curve, cohort compounding, cash roll-forward — all formulas.
B25: OUT_SUMMARY | C25: The one-page answer.
B26: CHECKS | C26: Excel vs SQL reconciliation, PASS/FAIL.
B28: PROVENANCE | C28: Synthetic data generated by src/01_generate_data.py (seeded, deterministic). The company is fictional; the method is not.

Sheet CONTROL
A1: CONTROL PANEL
A3: Scenario (pick one) | B3: selective | C3: <- blue cell: change this and the whole model moves
A4: Scenario column index | B4: =MATCH($B$3,DATA_SCENARIOS!$B$1:$D$1,0)
A6: ASSUMPTIONS (blue = editable input)
A7: Cash on hand ($) | B7: 6100000 | C7: As at 2026-08-31, per the CEO
A8: Board minimum runway (months) | B8: 18 | C8: The guardrail the board applies
A9: CAC payback hurdle (months) | B9: 18 | C9: Set equal to runway: we cannot fund a payback longer than our cash
A10: Holt alpha (level) | B10: 0.6 | C10: Grid-searched on in-sample one-step SSE in src/04
A11: Holt beta (trend) | B11: 0.45 | C11: Same fit. Holt won the rolling-origin backtest
A12: COGS % of revenue | B12: 0.21717207 | C12: Trailing 3 months
A13: S&M % of revenue (base book) | B13: 0.65075251 | C13: Current spending policy held constant
A14: R&D $/month at month 0 | B14: 325359.52 | C14: Headcount held flat
A15: G&A $/month at month 0 | B15: 138525.79 | C15: Headcount held flat
A16: Opex inflation (annual) | B16: 0.025 | C16: Applied to R&D and G&A
A17: SDR meetings/rep at small team | B17: 12.5 | C17: Observed when the team was 4 or fewer
A18: SDR saturation team size | B18: 4 | C18: Above this, meetings per rep decay
... A24: Paid Social new MRR run-rate ($/mo) | B24: 1170 | C24: Trailing 3 months — lost if the channel is switched off
A26: ACTIVE SCENARIO PARAMETERS (driven by B3)
A27: sdr_heads_added | B27: =INDEX(DATA_SCENARIOS!$B$2:$D$12,MATCH($A27,DATA_SCENARIOS!$A$2:$A$12,0),$B$4)
A28: list_overlap | B28: =INDEX(DATA_SCENARIOS!$B$2:$D$12,MATCH($A28,DATA_SCENARIOS!$A$2:$A$12,0),$B$4)
A29: monthly_cost | B29: =INDEX(DATA_SCENARIOS!$B$2:$D$12,MATCH($A29,DATA_SCENARIOS!$A$2:$A$12,0),$B$4)
A30: hire_lag_months | B30: =INDEX(DATA_SCENARIOS!$B$2:$D$12,MATCH($A30,DATA_SCENARIOS!$A$2:$A$12,0),$B$4)
A31: ramp_month_1 | B31: =INDEX(DATA_SCENARIOS!$B$2:$D$12,MATCH($A31,DATA_SCENARIOS!$A$2:$A$12,0),$B$4)
A32: ramp_month_2 | B32: =INDEX(DATA_SCENARIOS!$B$2:$D$12,MATCH($A32,DATA_SCENARIOS!$A$2:$A$12,0),$B$4)
A33: ramp_month_3 | B33: =INDEX(DATA_SCENARIOS!$B$2:$D$12,MATCH($A33,DATA_SCENARIOS!$A$2:$A$12,0),$B$4)
A34: seg_mix_SMB | B34: =INDEX(DATA_SCENARIOS!$B$2:$D$12,MATCH($A34,DATA_SCENARIOS!$A$2:$A$12,0),$B$4)
A35: seg_mix_MidMarket | B35: =INDEX(DATA_SCENARIOS!$B$2:$D$12,MATCH($A35,DATA_SCENARIOS!$A$2:$A$12,0),$B$4)
A36: seg_mix_Enterprise | B36: =INDEX(DATA_SCENARIOS!$B$2:$D$12,MATCH($A36,DATA_SCENARIOS!$A$2:$A$12,0),$B$4)
A37: paid_social_cut_pct | B37: =INDEX(DATA_SCENARIOS!$B$2:$D$12,MATCH($A37,DATA_SCENARIOS!$A$2:$A$12,0),$B$4)

Sheet DATA_SCENARIOS
A1: parameter | B1: base | C1: sales_proposal | D1: selective | E1: note
A2: sdr_heads_added | B2: 0 | C2: 9 | D2: 5 | E2: SDRs added on top of today's team
A3: list_overlap | B3: 1 | C3: 1 | D3: 0.4 | E3: 1.00 = new reps work the SAME account list; 0.00 = wholly new territory
A4: monthly_cost | B4: 0 | C4: 180000 | D4: 88500 | E4: Fully-loaded build-up: reps, managers, AEs, SEs, tooling
A5: hire_lag_months | B5: 0 | C5: 2 | D5: 2 | E5: Requisition opened -> seat filled
A6: ramp_month_1 | B6: 1 | C6: 0.35 | D6: 0.35 | E6: Share of full productivity, month 1 after start
A7: ramp_month_2 | B7: 1 | C7: 0.7 | D7: 0.7 | E7: month 2
A8: ramp_month_3 | B8: 1 | C8: 1 | D8: 1 | E8: month 3 onwards
A9: seg_mix_SMB | B9: 0 | C9: 0.06 | D9: 0.02 | E9: Share of the pod's won logos
A10: seg_mix_MidMarket | B10: 0 | C10: 0.66 | D10: 0.4
A11: seg_mix_Enterprise | B11: 0 | C11: 0.28 | D11: 0.58
A12: paid_social_cut_pct | B12: 0 | C12: 0 | D12: 1 | E12: 1.00 = channel switched off
A14: label | B14: Base - hold the line | C14: Sales proposal - double the SDR team (+$180k/mo) | D14: Selective - 5-rep Enterprise pod, funded by retiring Paid Social

Sheet DATA_ACTUALS
A1: month | B1: month_index | C1: mrr | D1: recognised_revenue | E1: carry_in_mrr | F1: new_mrr | G1: expansion_mrr | H1: reactivation_mrr | I1: contraction_mrr | J1: churn_mrr | K1: cogs | L1: sm | M1: rd | N1: ga | O1: total_cost | P1: net_burn | Q1: nrr_m
A2: 2023-09 | B2: 1 | C2: 316463 | D2: 314849.68 | E2: 305791 | F2: 10672 | G2: 0 | H2: 0 | I2: 0 | J2: 0 | K2: 70494.46 | L2: 195456.4 | M2: 161000 | N2: 86500 | O2: 513450.86 | P2: 198601.18 | Q2: 1
A3: 2023-10 | B3: 2 | C3: 318572 | D3: 318154.65 | E3: 0 | F3: 3750 | G3: 2243 | H3: 0 | I3: 466 | J3: 3418 | K3: 70724.35 | L3: 191652.26 | M3: 161294 | N3: 87000 | O3: 510670.61 | P3: 192515.96 | Q3: 0.99481456
A4: 2023-11 | B4: 3 | C4: 327036 | D4: 325445.1 | E4: 0 | F4: 9806 | G4: 2080 | H4: 0 | I4: 855 | J4: 2567 | K4: 71646.93 | L4: 201979.7 | M4: 161592.12 | N4: 87506.25 | O4: 522725 | P4: 197279.9 | Q4: 0.99578745
A5: 2023-12 | B5: 4 | C5: 328619 | D5: 326513.68 | E5: 0 | F5: 1674 | G5: 3171 | H5: 0 | I5: 645 | J5: 2617 | K5: 83819.47 | L5: 211035.54 | M5: 179394.41 | N5: 88018.83 | O5: 562268.25 | P5: 235754.57 | Q5: 0.99972174
A6: 2024-01 | B6: 5 | C6: 340008 | D6: 339518.5 | E6: 0 | F6: 10732 | G6: 3255 | H6: 0 | I6: 1044 | J6: 1554 | K6: 85094.88 | L6: 225116.81 | M6: 179700.93 | N6: 88537.81 | O6: 578450.43 | P6: 238931.93 | Q6: 1.0019993
A7: 2024-02 | B7: 6 | C7: 347319 | D7: 346256.23 | E7: 0 | F7: 9438 | G7: 2615 | H7: 351 | I7: 609 | J7: 4484 | K7: 85857.77 | L7: 251366.33 | M7: 180011.74 | N7: 89063.29 | O7: 606299.13 | P7: 260042.9 | Q7: 0.99271194
A8: 2024-03 | B8: 7 | C8: 366374 | D8: 364074.5 | E8: 0 | F8: 20122 | G8: 3136 | H8: 0 | I8: 916 | J8: 3287 | K8: 87934.76 | L8: 267640.89 | M8: 180326.9 | N8: 89595.33 | O8: 625497.88 | P8: 261423.38 | Q8: 0.9969279
A9: 2024-04 | B9: 8 | C9: 377705 | D9: 374530.31 | E9: 0 | F9: 14884 | G9: 1944 | H9: 0 | I9: 544 | J9: 4953 | K9: 89169.85 | L9: 263806.34 | M9: 198146.48 | N9: 90134.02 | O9: 641256.69 | P9: 266726.38 | Q9: 0.99030226
A10: 2024-05 | B10: 9 | C10: 380074 | D10: 375426.44 | E10: 0 | F10: 8710 | G10: 3129 | H10: 0 | I10: 874 | J10: 8596 | K10: 89428.06 | L10: 260276.5 | M10: 198470.53 | N10: 90679.44 | O10: 638854.53 | P10: 263428.09 | Q10: 0.98321177
A11: 2024-06 | B11: 10 | C11: 383079 | D11: 382600.53 | E11: 0 | F11: 3927 | G11: 2648 | H11: 0 | I11: 567 | J11: 3003 | K11: 101755.61 | L11: 288917.98 | M11: 198799.12 | N11: 106731.69 | O11: 696204.4 | P11: 313603.87 | Q11: 0.99757416
A12: 2024-07 | B12: 11 | C12: 388364 | D12: 387158.26 | E12: 0 | F12: 14986 | G12: 3000 | H12: 0 | I12: 1325 | J12: 11376 | K12: 103083.45 | L12: 305571.38 | M12: 199132.31 | N12: 107290.83 | O12: 715077.97 | P12: 327919.71 | Q12: 0.97467624
A13: 2024-08 | B13: 12 | C13: 399466 | D13: 397086.13 | E13: 0 | F13: 6410 | G13: 2339 | H13: 7502 | I13: 857 | J13: 4292 | K13: 103541.8 | L13: 298419.77 | M13: 216970.16 | N13: 107856.97 | O13: 726788.7 | P13: 329702.57 | Q13: 0.99276452
... A37: 2026-08 | B37: 36 | C37: 1031192.8 | D37: 1025405.2 | E37: 0 | F37: 27328 | G37: 13863.2 | H37: 0 | I37: 1708.28 | J37: 5471.86 | K37: 220400.01 | L37: 654867.05 | M37: 331662.35 | N37: 139285.43 | O37: 1346214.8 | P37: 320809.59 | Q37: 1.0067019

Sheet DATA_SEGMENTS
A1: segment | B1: gross_margin | C1: monthly_nrr | D1: outbound_acv | E1: sales_cycle_lag_months | F1: paid_social_mix | G1: sales_effort_index
A2: SMB | B2: 0.82 | C2: 0.98265622 | D2: 8556 | E2: 1 | F2: 0.68069984 | G2: 1
A3: MidMarket | B3: 0.78 | C3: 1.0013552 | D3: 26764.138 | E3: 2 | F3: 0.31930016 | G3: 2.2
A4: Enterprise | B4: 0.735 | C4: 1.0125083 | D4: 93486.462 | E4: 4 | F4: 0 | G4: 4

Sheet DATA_CHANNELS
A1: channel | B1: n_wins | C1: new_acv | D1: avg_acv | E1: gross_margin | F1: program_spend | G1: sdr_payroll | H1: shared_sales_alloc | I1: commission | J1: monthly_logo_churn_pct | K1: monthly_nrr_pct
A2: events | B2: 2 | C2: 118140 | D2: 59070 | E2: 0.742 | F2: 289850 | G2: 0 | H2: 50316 | I2: 11814 | J2: 0 | K2: 1.0291
A3: inbound_content | B3: 23 | C3: 611340 | D3: 26580 | E3: 0.773 | F3: 303167 | G3: 0 | H3: 374407 | I3: 61134 | J3: 0.0117 | K3: 1.0054
A4: outbound_sdr | B4: 46 | C4: 2025708 | D4: 44037 | E4: 0.754 | F4: 186000 | G4: 1572000 | H4: 1361482 | I4: 202571 | J4: 0.006 | K4: 1.0089
A5: paid_search | B5: 57 | C5: 851304 | D5: 14935 | E5: 0.788 | F5: 537200 | G5: 0 | H5: 590469 | I5: 85130 | J5: 0.0189 | K5: 0.9978
A6: paid_social | B6: 36 | C6: 241428 | D6: 6706 | E6: 0.807 | F6: 768000 | G6: 0 | H6: 319652 | I6: 24143 | J6: 0.0634 | K6: 0.9517
A7: partner | B7: 16 | C7: 597828 | D7: 37364 | E7: 0.767 | F7: 205200 | G7: 0 | H7: 213101 | I7: 59783 | J7: 0.013 | K7: 1.003

Sheet CALC_UNIT_ECON
A1: CHANNEL UNIT ECONOMICS — trailing 12 months, all formulas
A2: LTV = monthly gross profit x (1 - NRR^60) / (1 - NRR). Finite 60-month horizon, observed net revenue retention.
A4: channel | B4: wins (12m) | C4: avg ACV | D4: total CAC spend | E4: CAC | F4: monthly gross profit | G4: CAC payback (months) | H4: LTV (60m, NRR based) | I4: LTV / CAC | J4: verdict vs hurdle
A5: =DATA_CHANNELS!A2 | B5: =DATA_CHANNELS!B2 | C5: =DATA_CHANNELS!D2 | D5: =DATA_CHANNELS!F2+DATA_CHANNELS!G2+DATA_CHANNELS!H2+DATA_CHANNELS!I2 | E5: =D5/B5 | F5: =C5/12*DATA_CHANNELS!E2 | G5: =IFERROR(E5/F5,"n/a") | H5: =IF(ABS(1-DATA_CHANNELS!K2)<0.0000001,F5*60,F5*(1-DATA_CHANNELS!K2^60)/(1-DATA_CHANNELS!K2)) | I5: =IFERROR(H5/E5,"n/a") | J5: =IF(G5<=CONTROL!$B$9,"PASS - within hurdle","FAIL - payback beyond runway")
A6: =DATA_CHANNELS!A3 | B6: =DATA_CHANNELS!B3 | C6: =DATA_CHANNELS!D3 | D6: =DATA_CHANNELS!F3+DATA_CHANNELS!G3+DATA_CHANNELS!H3+DATA_CHANNELS!I3 | E6: =D6/B6 | F6: =C6/12*DATA_CHANNELS!E3 | G6: =IFERROR(E6/F6,"n/a") | H6: =IF(ABS(1-DATA_CHANNELS!K3)<0.0000001,F6*60,F6*(1-DATA_CHANNELS!K3^60)/(1-DATA_CHANNELS!K3)) | I6: =IFERROR(H6/E6,"n/a") | J6: =IF(G6<=CONTROL!$B$9,"PASS - within hurdle","FAIL - payback beyond runway")
A7: =DATA_CHANNELS!A4 | B7: =DATA_CHANNELS!B4 | C7: =DATA_CHANNELS!D4 | D7: =DATA_CHANNELS!F4+DATA_CHANNELS!G4+DATA_CHANNELS!H4+DATA_CHANNELS!I4 | E7: =D7/B7 | F7: =C7/12*DATA_CHANNELS!E4 | G7: =IFERROR(E7/F7,"n/a") | H7: =IF(ABS(1-DATA_CHANNELS!K4)<0.0000001,F7*60,F7*(1-DATA_CHANNELS!K4^60)/(1-DATA_CHANNELS!K4)) | I7: =IFERROR(H7/E7,"n/a") | J7: =IF(G7<=CONTROL!$B$9,"PASS - within hurdle","FAIL - payback beyond runway")
A8: =DATA_CHANNELS!A5 | B8: =DATA_CHANNELS!B5 | C8: =DATA_CHANNELS!D5 | D8: =DATA_CHANNELS!F5+DATA_CHANNELS!G5+DATA_CHANNELS!H5+DATA_CHANNELS!I5 | E8: =D8/B8 | F8: =C8/12*DATA_CHANNELS!E5 | G8: =IFERROR(E8/F8,"n/a") | H8: =IF(ABS(1-DATA_CHANNELS!K5)<0.0000001,F8*60,F8*(1-DATA_CHANNELS!K5^60)/(1-DATA_CHANNELS!K5)) | I8: =IFERROR(H8/E8,"n/a") | J8: =IF(G8<=CONTROL!$B$9,"PASS - within hurdle","FAIL - payback beyond runway")
A9: =DATA_CHANNELS!A6 | B9: =DATA_CHANNELS!B6 | C9: =DATA_CHANNELS!D6 | D9: =DATA_CHANNELS!F6+DATA_CHANNELS!G6+DATA_CHANNELS!H6+DATA_CHANNELS!I6 | E9: =D9/B9 | F9: =C9/12*DATA_CHANNELS!E6 | G9: =IFERROR(E9/F9,"n/a") | H9: =IF(ABS(1-DATA_CHANNELS!K6)<0.0000001,F9*60,F9*(1-DATA_CHANNELS!K6^60)/(1-DATA_CHANNELS!K6)) | I9: =IFERROR(H9/E9,"n/a") | J9: =IF(G9<=CONTROL!$B$9,"PASS - within hurdle","FAIL - payback beyond runway")
A10: =DATA_CHANNELS!A7 | B10: =DATA_CHANNELS!B7 | C10: =DATA_CHANNELS!D7 | D10: =DATA_CHANNELS!F7+DATA_CHANNELS!G7+DATA_CHANNELS!H7+DATA_CHANNELS!I7 | E10: =D10/B10 | F10: =C10/12*DATA_CHANNELS!E7 | G10: =IFERROR(E10/F10,"n/a") | H10: =IF(ABS(1-DATA_CHANNELS!K7)<0.0000001,F10*60,F10*(1-DATA_CHANNELS!K7^60)/(1-DATA_CHANNELS!K7)) | I10: =IFERROR(H10/E10,"n/a") | J10: =IF(G10<=CONTROL!$B$9,"PASS - within hurdle","FAIL - payback beyond runway")

Sheet CALC_FORECAST
A1: 18-MONTH FORECAST — every cell below is a formula
A2: Block 1 recreates the Holt recursion that won the backtest. Block 2 projects it, adds the scenario, and rolls cash forward.
A4: BLOCK 1 — Holt smoothing over actual MRR
A5: month | B5: actual MRR | C5: level | D5: trend
A6: =DATA_ACTUALS!A2 | B6: =DATA_ACTUALS!C2 | C6: =B6 | D6: =B7-B6
A7: =DATA_ACTUALS!A3 | B7: =DATA_ACTUALS!C3 | C7: =CONTROL!$B$10*B7+(1-CONTROL!$B$10)*(C6+D6) | D7: =CONTROL!$B$11*(C7-C6)+(1-CONTROL!$B$11)*D6
A8: =DATA_ACTUALS!A4 | B8: =DATA_ACTUALS!C4 | C8: =CONTROL!$B$10*B8+(1-CONTROL!$B$10)*(C7+D7) | D8: =CONTROL!$B$11*(C8-C7)+(1-CONTROL!$B$11)*D7
A9: =DATA_ACTUALS!A5 | B9: =DATA_ACTUALS!C5 | C9: =CONTROL!$B$10*B9+(1-CONTROL!$B$10)*(C8+D8) | D9: =CONTROL!$B$11*(C9-C8)+(1-CONTROL!$B$11)*D8
A10: =DATA_ACTUALS!A6 | B10: =DATA_ACTUALS!C6 | C10: =CONTROL!$B$10*B10+(1-CONTROL!$B$10)*(C9+D9) | D10: =CONTROL!$B$11*(C10-C9)+(1-CONTROL!$B$11)*D9
A11: =DATA_ACTUALS!A7 | B11: =DATA_ACTUALS!C7 | C11: =CONTROL!$B$10*B11+(1-CONTROL!$B$10)*(C10+D10) | D11: =CONTROL!$B$11*(C11-C10)+(1-CONTROL!$B$11)*D10
A12: =DATA_ACTUALS!A8 | B12: =DATA_ACTUALS!C8 | C12: =CONTROL!$B$10*B12+(1-CONTROL!$B$10)*(C11+D11) | D12: =CONTROL!$B$11*(C12-C11)+(1-CONTROL!$B$11)*D11
A13: =DATA_ACTUALS!A9 | B13: =DATA_ACTUALS!C9 | C13: =CONTROL!$B$10*B13+(1-CONTROL!$B$10)*(C12+D12) | D13: =CONTROL!$B$11*(C13-C12)+(1-CONTROL!$B$11)*D12
A14: =DATA_ACTUALS!A10 | B14: =DATA_ACTUALS!C10 | C14: =CONTROL!$B$10*B14+(1-CONTROL!$B$10)*(C13+D13) | D14: =CONTROL!$B$11*(C14-C13)+(1-CONTROL!$B$11)*D13
A15: =DATA_ACTUALS!A11 | B15: =DATA_ACTUALS!C11 | C15: =CONTROL!$B$10*B15+(1-CONTROL!$B$10)*(C14+D14) | D15: =CONTROL!$B$11*(C15-C14)+(1-CONTROL!$B$11)*D14
A16: =DATA_ACTUALS!A12 | B16: =DATA_ACTUALS!C12 | C16: =CONTROL!$B$10*B16+(1-CONTROL!$B$10)*(C15+D15) | D16: =CONTROL!$B$11*(C16-C15)+(1-CONTROL!$B$11)*D15
A17: =DATA_ACTUALS!A13 | B17: =DATA_ACTUALS!C13 | C17: =CONTROL!$B$10*B17+(1-CONTROL!$B$10)*(C16+D16) | D17: =CONTROL!$B$11*(C17-C16)+(1-CONTROL!$B$11)*D16
A18: =DATA_ACTUALS!A14 | B18: =DATA_ACTUALS!C14 | C18: =CONTROL!$B$10*B18+(1-CONTROL!$B$10)*(C17+D17) | D18: =CONTROL!$B$11*(C18-C17)+(1-CONTROL!$B$11)*D17
... A41: =DATA_ACTUALS!A37 | B41: =DATA_ACTUALS!C37 | C41: =CONTROL!$B$10*B41+(1-CONTROL!$B$10)*(C40+D40) | D41: =CONTROL!$B$11*(C41-C40)+(1-CONTROL!$B$11)*D40
A43: BLOCK 2 — scenario forecast and cash roll-forward
A44: month | B44: k | C44: base MRR | D44: ramp | E44: eff. added heads | F44: existing eff. team | G44: new-rep eff. team | H44: incr. meetings | I44: incr. wins | J44: booked SMB | K44: booked MidMkt | L44: booked Ent | M44: live SMB | N44: live MidMkt | O44: live Ent | P44: delta MRR | Q44: MRR | R44: COGS | S44: incr. S&M | T44: paid social saving | U44: incr. commission | V44: S&M | W44: R&D | X44: G&A | Y44: total cost | Z44: net burn | AA44: cash
A45: seed | B45: 0 | M45: 0 | N45: 0 | O45: 0 | P45: 0 | AA45: =CONTROL!$B$7
A46: 2026-09 | B46: 1 | C46: =$C$41+$D$41*B46 | D46: =IF(B46-CONTROL!$B$30<=0,0,IF(B46-CONTROL!$B$30=1,CONTROL!$B$31,IF(B46-CONTROL!$B$30=2,CONTROL!$B$32,CONTROL!$B$33))) | E46: =CONTROL!$B$27*D46 | F46: =CONTROL!$B$20+E46*CONTROL!$B$28 | G46: =CONTROL!$B$20*CONTROL!$B$28+E46 | H46: =IF(E46<=0,0,CONTROL!$B$20*IF(F46<=CONTROL!$B$18,CONTROL!$B$17,CONTROL!$B$17*(CONTROL!$B$18/F46)^CONTROL!$B$19)+E46*IF(G46<=CONTROL!$B$18,CONTROL!$B$17,CONTROL!$B$17*(CONTROL!$B$18/G46)^CONTROL!$B$19)-CONTROL!$B$20*IF(CONTROL!$B$20<=CONTROL!$B$18,CONTROL!$B$17,CONTROL!$B$17*(CONTROL!$B$18/CONTROL!$B$20)^CONTROL!$B$19)) | I46: =H46*CONTROL!$B$21 | J46: =I46*CONTROL!$B$34*DATA_SEGMENTS!$D$2/12-CONTROL!$B$37*CONTROL!$B$24*DATA_SEGMENTS!$F$2 | K46: =I46*CONTROL!$B$35*DATA_SEGMENTS!$D$3/12-CONTROL!$B$37*CONTROL!$B$24*DATA_SEGMENTS!$F$3 | L46: =I46*CONTROL!$B$36*DATA_SEGMENTS!$D$4/12-CONTROL!$B$37*CONTROL!$B$24*DATA_SEGMENTS!$F$4 | M46: =IF(B46<=DATA_SEGMENTS!$E$2,0,M45*DATA_SEGMENTS!$C$2+INDEX($J$46:$J$63,B46-DATA_SEGMENTS!$E$2)) | N46: =IF(B46<=DATA_SEGMENTS!$E$3,0,N45*DATA_SEGMENTS!$C$3+INDEX($K$46:$K$63,B46-DATA_SEGMENTS!$E$3)) | O46: =IF(B46<=DATA_SEGMENTS!$E$4,0,O45*DATA_SEGMENTS!$C$4+INDEX($L$46:$L$63,B46-DATA_SEGMENTS!$E$4)) | P46: =M46+N46+O46 | Q46: =C46+P46 | R46: =Q46*CONTROL!$B$12 | S46: =IF(B46>CONTROL!$B$30,CONTROL!$B$29,0) | T46: =-CONTROL!$B$37*CONTROL!$B$23 | U46: =(J46+K46+L46)*12*CONTROL!$B$22 | V46: =C46*CONTROL!$B$13+S46+T46+U46 | W46: =CONTROL!$B$14*(1+CONTROL!$B$16)^(B46/12) | X46: =CONTROL!$B$15*(1+CONTROL!$B$16)^(B46/12) | Y46: =R46+V46+W46+X46 | Z46: =Y46-Q46 | AA46: =AA45-Z46
A47: 2026-10 | B47: 2 | C47: =$C$41+$D$41*B47 | D47: =IF(B47-CONTROL!$B$30<=0,0,IF(B47-CONTROL!$B$30=1,CONTROL!$B$31,IF(B47-CONTROL!$B$30=2,CONTROL!$B$32,CONTROL!$B$33))) | E47: =CONTROL!$B$27*D47 | F47: =CONTROL!$B$20+E47*CONTROL!$B$28 | G47: =CONTROL!$B$20*CONTROL!$B$28+E47 | H47: =IF(E47<=0,0,CONTROL!$B$20*IF(F47<=CONTROL!$B$18,CONTROL!$B$17,CONTROL!$B$17*(CONTROL!$B$18/F47)^CONTROL!$B$19)+E47*IF(G47<=CONTROL!$B$18,CONTROL!$B$17,CONTROL!$B$17*(CONTROL!$B$18/G47)^CONTROL!$B$19)-CONTROL!$B$20*IF(CONTROL!$B$20<=CONTROL!$B$18,CONTROL!$B$17,CONTROL!$B$17*(CONTROL!$B$18/CONTROL!$B$20)^CONTROL!$B$19)) | I47: =H47*CONTROL!$B$21 | J47: =I47*CONTROL!$B$34*DATA_SEGMENTS!$D$2/12-CONTROL!$B$37*CONTROL!$B$24*DATA_SEGMENTS!$F$2 | K47: =I47*CONTROL!$B$35*DATA_SEGMENTS!$D$3/12-CONTROL!$B$37*CONTROL!$B$24*DATA_SEGMENTS!$F$3 | L47: =I47*CONTROL!$B$36*DATA_SEGMENTS!$D$4/12-CONTROL!$B$37*CONTROL!$B$24*DATA_SEGMENTS!$F$4 | M47: =IF(B47<=DATA_SEGMENTS!$E$2,0,M46*DATA_SEGMENTS!$C$2+INDEX($J$46:$J$63,B47-DATA_SEGMENTS!$E$2)) | N47: =IF(B47<=DATA_SEGMENTS!$E$3,0,N46*DATA_SEGMENTS!$C$3+INDEX($K$46:$K$63,B47-DATA_SEGMENTS!$E$3)) | O47: =IF(B47<=DATA_SEGMENTS!$E$4,0,O46*DATA_SEGMENTS!$C$4+INDEX($L$46:$L$63,B47-DATA_SEGMENTS!$E$4)) | P47: =M47+N47+O47 | Q47: =C47+P47 | R47: =Q47*CONTROL!$B$12 | S47: =IF(B47>CONTROL!$B$30,CONTROL!$B$29,0) | T47: =-CONTROL!$B$37*CONTROL!$B$23 | U47: =(J47+K47+L47)*12*CONTROL!$B$22 | V47: =C47*CONTROL!$B$13+S47+T47+U47 | W47: =CONTROL!$B$14*(1+CONTROL!$B$16)^(B47/12) | X47: =CONTROL!$B$15*(1+CONTROL!$B$16)^(B47/12) | Y47: =R47+V47+W47+X47 | Z47: =Y47-Q47 | AA47: =AA46-Z47
A48: 2026-11 | B48: 3 | C48: =$C$41+$D$41*B48 | D48: =IF(B48-CONTROL!$B$30<=0,0,IF(B48-CONTROL!$B$30=1,CONTROL!$B$31,IF(B48-CONTROL!$B$30=2,CONTROL!$B$32,CONTROL!$B$33))) | E48: =CONTROL!$B$27*D48 | F48: =CONTROL!$B$20+E48*CONTROL!$B$28 | G48: =CONTROL!$B$20*CONTROL!$B$28+E48 | H48: =IF(E48<=0,0,CONTROL!$B$20*IF(F48<=CONTROL!$B$18,CONTROL!$B$17,CONTROL!$B$17*(CONTROL!$B$18/F48)^CONTROL!$B$19)+E48*IF(G48<=CONTROL!$B$18,CONTROL!$B$17,CONTROL!$B$17*(CONTROL!$B$18/G48)^CONTROL!$B$19)-CONTROL!$B$20*IF(CONTROL!$B$20<=CONTROL!$B$18,CONTROL!$B$17,CONTROL!$B$17*(CONTROL!$B$18/CONTROL!$B$20)^CONTROL!$B$19)) | I48: =H48*CONTROL!$B$21 | J48: =I48*CONTROL!$B$34*DATA_SEGMENTS!$D$2/12-CONTROL!$B$37*CONTROL!$B$24*DATA_SEGMENTS!$F$2 | K48: =I48*CONTROL!$B$35*DATA_SEGMENTS!$D$3/12-CONTROL!$B$37*CONTROL!$B$24*DATA_SEGMENTS!$F$3 | L48: =I48*CONTROL!$B$36*DATA_SEGMENTS!$D$4/12-CONTROL!$B$37*CONTROL!$B$24*DATA_SEGMENTS!$F$4 | M48: =IF(B48<=DATA_SEGMENTS!$E$2,0,M47*DATA_SEGMENTS!$C$2+INDEX($J$46:$J$63,B48-DATA_SEGMENTS!$E$2)) | N48: =IF(B48<=DATA_SEGMENTS!$E$3,0,N47*DATA_SEGMENTS!$C$3+INDEX($K$46:$K$63,B48-DATA_SEGMENTS!$E$3)) | O48: =IF(B48<=DATA_SEGMENTS!$E$4,0,O47*DATA_SEGMENTS!$C$4+INDEX($L$46:$L$63,B48-DATA_SEGMENTS!$E$4)) | P48: =M48+N48+O48 | Q48: =C48+P48 | R48: =Q48*CONTROL!$B$12 | S48: =IF(B48>CONTROL!$B$30,CONTROL!$B$29,0) | T48: =-CONTROL!$B$37*CONTROL!$B$23 | U48: =(J48+K48+L48)*12*CONTROL!$B$22 | V48: =C48*CONTROL!$B$13+S48+T48+U48 | W48: =CONTROL!$B$14*(1+CONTROL!$B$16)^(B48/12) | X48: =CONTROL!$B$15*(1+CONTROL!$B$16)^(B48/12) | Y48: =R48+V48+W48+X48 | Z48: =Y48-Q48 | AA48: =AA47-Z48
A49: 2026-12 | B49: 4 | C49: =$C$41+$D$41*B49 | D49: =IF(B49-CONTROL!$B$30<=0,0,IF(B49-CONTROL!$B$30=1,CONTROL!$B$31,IF(B49-CONTROL!$B$30=2,CONTROL!$B$32,CONTROL!$B$33))) | E49: =CONTROL!$B$27*D49 | F49: =CONTROL!$B$20+E49*CONTROL!$B$28 | G49: =CONTROL!$B$20*CONTROL!$B$28+E49 | H49: =IF(E49<=0,0,CONTROL!$B$20*IF(F49<=CONTROL!$B$18,CONTROL!$B$17,CONTROL!$B$17*(CONTROL!$B$18/F49)^CONTROL!$B$19)+E49*IF(G49<=CONTROL!$B$18,CONTROL!$B$17,CONTROL!$B$17*(CONTROL!$B$18/G49)^CONTROL!$B$19)-CONTROL!$B$20*IF(CONTROL!$B$20<=CONTROL!$B$18,CONTROL!$B$17,CONTROL!$B$17*(CONTROL!$B$18/CONTROL!$B$20)^CONTROL!$B$19)) | I49: =H49*CONTROL!$B$21 | J49: =I49*CONTROL!$B$34*DATA_SEGMENTS!$D$2/12-CONTROL!$B$37*CONTROL!$B$24*DATA_SEGMENTS!$F$2 | K49: =I49*CONTROL!$B$35*DATA_SEGMENTS!$D$3/12-CONTROL!$B$37*CONTROL!$B$24*DATA_SEGMENTS!$F$3 | L49: =I49*CONTROL!$B$36*DATA_SEGMENTS!$D$4/12-CONTROL!$B$37*CONTROL!$B$24*DATA_SEGMENTS!$F$4 | M49: =IF(B49<=DATA_SEGMENTS!$E$2,0,M48*DATA_SEGMENTS!$C$2+INDEX($J$46:$J$63,B49-DATA_SEGMENTS!$E$2)) | N49: =IF(B49<=DATA_SEGMENTS!$E$3,0,N48*DATA_SEGMENTS!$C$3+INDEX($K$46:$K$63,B49-DATA_SEGMENTS!$E$3)) | O49: =IF(B49<=DATA_SEGMENTS!$E$4,0,O48*DATA_SEGMENTS!$C$4+INDEX($L$46:$L$63,B49-DATA_SEGMENTS!$E$4)) | P49: =M49+N49+O49 | Q49: =C49+P49 | R49: =Q49*CONTROL!$B$12 | S49: =IF(B49>CONTROL!$B$30,CONTROL!$B$29,0) | T49: =-CONTROL!$B$37*CONTROL!$B$23 | U49: =(J49+K49+L49)*12*CONTROL!$B$22 | V49: =C49*CONTROL!$B$13+S49+T49+U49 | W49: =CONTROL!$B$14*(1+CONTROL!$B$16)^(B49/12) | X49: =CONTROL!$B$15*(1+CONTROL!$B$16)^(B49/12) | Y49: =R49+V49+W49+X49 | Z49: =Y49-Q49 | AA49: =AA48-Z49
A50: 2027-01 | B50: 5 | C50: =$C$41+$D$41*B50 | D50: =IF(B50-CONTROL!$B$30<=0,0,IF(B50-CONTROL!$B$30=1,CONTROL!$B$31,IF(B50-CONTROL!$B$30=2,CONTROL!$B$32,CONTROL!$B$33))) | E50: =CONTROL!$B$27*D50 | F50: =CONTROL!$B$20+E50*CONTROL!$B$28 | G50: =CONTROL!$B$20*CONTROL!$B$28+E50 | H50: =IF(E50<=0,0,CONTROL!$B$20*IF(F50<=CONTROL!$B$18,CONTROL!$B$17,CONTROL!$B$17*(CONTROL!$B$18/F50)^CONTROL!$B$19)+E50*IF(G50<=CONTROL!$B$18,CONTROL!$B$17,CONTROL!$B$17*(CONTROL!$B$18/G50)^CONTROL!$B$19)-CONTROL!$B$20*IF(CONTROL!$B$20<=CONTROL!$B$18,CONTROL!$B$17,CONTROL!$B$17*(CONTROL!$B$18/CONTROL!$B$20)^CONTROL!$B$19)) | I50: =H50*CONTROL!$B$21 | J50: =I50*CONTROL!$B$34*DATA_SEGMENTS!$D$2/12-CONTROL!$B$37*CONTROL!$B$24*DATA_SEGMENTS!$F$2 | K50: =I50*CONTROL!$B$35*DATA_SEGMENTS!$D$3/12-CONTROL!$B$37*CONTROL!$B$24*DATA_SEGMENTS!$F$3 | L50: =I50*CONTROL!$B$36*DATA_SEGMENTS!$D$4/12-CONTROL!$B$37*CONTROL!$B$24*DATA_SEGMENTS!$F$4 | M50: =IF(B50<=DATA_SEGMENTS!$E$2,0,M49*DATA_SEGMENTS!$C$2+INDEX($J$46:$J$63,B50-DATA_SEGMENTS!$E$2)) | N50: =IF(B50<=DATA_SEGMENTS!$E$3,0,N49*DATA_SEGMENTS!$C$3+INDEX($K$46:$K$63,B50-DATA_SEGMENTS!$E$3)) | O50: =IF(B50<=DATA_SEGMENTS!$E$4,0,O49*DATA_SEGMENTS!$C$4+INDEX($L$46:$L$63,B50-DATA_SEGMENTS!$E$4)) | P50: =M50+N50+O50 | Q50: =C50+P50 | R50: =Q50*CONTROL!$B$12 | S50: =IF(B50>CONTROL!$B$30,CONTROL!$B$29,0) | T50: =-CONTROL!$B$37*CONTROL!$B$23 | U50: =(J50+K50+L50)*12*CONTROL!$B$22 | V50: =C50*CONTROL!$B$13+S50+T50+U50 | W50: =CONTROL!$B$14*(1+CONTROL!$B$16)^(B50/12) | X50: =CONTROL!$B$15*(1+CONTROL!$B$16)^(B50/12) | Y50: =R50+V50+W50+X50 | Z50: =Y50-Q50 | AA50: =AA49-Z50
A51: 2027-02 | B51: 6 | C51: =$C$41+$D$41*B51 | D51: =IF(B51-CONTROL!$B$30<=0,0,IF(B51-CONTROL!$B$30=1,CONTROL!$B$31,IF(B51-CONTROL!$B$30=2,CONTROL!$B$32,CONTROL!$B$33))) | E51: =CONTROL!$B$27*D51 | F51: =CONTROL!$B$20+E51*CONTROL!$B$28 | G51: =CONTROL!$B$20*CONTROL!$B$28+E51 | H51: =IF(E51<=0,0,CONTROL!$B$20*IF(F51<=CONTROL!$B$18,CONTROL!$B$17,CONTROL!$B$17*(CONTROL!$B$18/F51)^CONTROL!$B$19)+E51*IF(G51<=CONTROL!$B$18,CONTROL!$B$17,CONTROL!$B$17*(CONTROL!$B$18/G51)^CONTROL!$B$19)-CONTROL!$B$20*IF(CONTROL!$B$20<=CONTROL!$B$18,CONTROL!$B$17,CONTROL!$B$17*(CONTROL!$B$18/CONTROL!$B$20)^CONTROL!$B$19)) | I51: =H51*CONTROL!$B$21 | J51: =I51*CONTROL!$B$34*DATA_SEGMENTS!$D$2/12-CONTROL!$B$37*CONTROL!$B$24*DATA_SEGMENTS!$F$2 | K51: =I51*CONTROL!$B$35*DATA_SEGMENTS!$D$3/12-CONTROL!$B$37*CONTROL!$B$24*DATA_SEGMENTS!$F$3 | L51: =I51*CONTROL!$B$36*DATA_SEGMENTS!$D$4/12-CONTROL!$B$37*CONTROL!$B$24*DATA_SEGMENTS!$F$4 | M51: =IF(B51<=DATA_SEGMENTS!$E$2,0,M50*DATA_SEGMENTS!$C$2+INDEX($J$46:$J$63,B51-DATA_SEGMENTS!$E$2)) | N51: =IF(B51<=DATA_SEGMENTS!$E$3,0,N50*DATA_SEGMENTS!$C$3+INDEX($K$46:$K$63,B51-DATA_SEGMENTS!$E$3)) | O51: =IF(B51<=DATA_SEGMENTS!$E$4,0,O50*DATA_SEGMENTS!$C$4+INDEX($L$46:$L$63,B51-DATA_SEGMENTS!$E$4)) | P51: =M51+N51+O51 | Q51: =C51+P51 | R51: =Q51*CONTROL!$B$12 | S51: =IF(B51>CONTROL!$B$30,CONTROL!$B$29,0) | T51: =-CONTROL!$B$37*CONTROL!$B$23 | U51: =(J51+K51+L51)*12*CONTROL!$B$22 | V51: =C51*CONTROL!$B$13+S51+T51+U51 | W51: =CONTROL!$B$14*(1+CONTROL!$B$16)^(B51/12) | X51: =CONTROL!$B$15*(1+CONTROL!$B$16)^(B51/12) | Y51: =R51+V51+W51+X51 | Z51: =Y51-Q51 | AA51: =AA50-Z51
A52: 2027-03 | B52: 7 | C52: =$C$41+$D$41*B52 | D52: =IF(B52-CONTROL!$B$30<=0,0,IF(B52-CONTROL!$B$30=1,CONTROL!$B$31,IF(B52-CONTROL!$B$30=2,CONTROL!$B$32,CONTROL!$B$33))) | E52: =CONTROL!$B$27*D52 | F52: =CONTROL!$B$20+E52*CONTROL!$B$28 | G52: =CONTROL!$B$20*CONTROL!$B$28+E52 | H52: =IF(E52<=0,0,CONTROL!$B$20*IF(F52<=CONTROL!$B$18,CONTROL!$B$17,CONTROL!$B$17*(CONTROL!$B$18/F52)^CONTROL!$B$19)+E52*IF(G52<=CONTROL!$B$18,CONTROL!$B$17,CONTROL!$B$17*(CONTROL!$B$18/G52)^CONTROL!$B$19)-CONTROL!$B$20*IF(CONTROL!$B$20<=CONTROL!$B$18,CONTROL!$B$17,CONTROL!$B$17*(CONTROL!$B$18/CONTROL!$B$20)^CONTROL!$B$19)) | I52: =H52*CONTROL!$B$21 | J52: =I52*CONTROL!$B$34*DATA_SEGMENTS!$D$2/12-CONTROL!$B$37*CONTROL!$B$24*DATA_SEGMENTS!$F$2 | K52: =I52*CONTROL!$B$35*DATA_SEGMENTS!$D$3/12-CONTROL!$B$37*CONTROL!$B$24*DATA_SEGMENTS!$F$3 | L52: =I52*CONTROL!$B$36*DATA_SEGMENTS!$D$4/12-CONTROL!$B$37*CONTROL!$B$24*DATA_SEGMENTS!$F$4 | M52: =IF(B52<=DATA_SEGMENTS!$E$2,0,M51*DATA_SEGMENTS!$C$2+INDEX($J$46:$J$63,B52-DATA_SEGMENTS!$E$2)) | N52: =IF(B52<=DATA_SEGMENTS!$E$3,0,N51*DATA_SEGMENTS!$C$3+INDEX($K$46:$K$63,B52-DATA_SEGMENTS!$E$3)) | O52: =IF(B52<=DATA_SEGMENTS!$E$4,0,O51*DATA_SEGMENTS!$C$4+INDEX($L$46:$L$63,B52-DATA_SEGMENTS!$E$4)) | P52: =M52+N52+O52 | Q52: =C52+P52 | R52: =Q52*CONTROL!$B$12 | S52: =IF(B52>CONTROL!$B$30,CONTROL!$B$29,0) | T52: =-CONTROL!$B$37*CONTROL!$B$23 | U52: =(J52+K52+L52)*12*CONTROL!$B$22 | V52: =C52*CONTROL!$B$13+S52+T52+U52 | W52: =CONTROL!$B$14*(1+CONTROL!$B$16)^(B52/12) | X52: =CONTROL!$B$15*(1+CONTROL!$B$16)^(B52/12) | Y52: =R52+V52+W52+X52 | Z52: =Y52-Q52 | AA52: =AA51-Z52
A53: 2027-04 | B53: 8 | C53: =$C$41+$D$41*B53 | D53: =IF(B53-CONTROL!$B$30<=0,0,IF(B53-CONTROL!$B$30=1,CONTROL!$B$31,IF(B53-CONTROL!$B$30=2,CONTROL!$B$32,CONTROL!$B$33))) | E53: =CONTROL!$B$27*D53 | F53: =CONTROL!$B$20+E53*CONTROL!$B$28 | G53: =CONTROL!$B$20*CONTROL!$B$28+E53 | H53: =IF(E53<=0,0,CONTROL!$B$20*IF(F53<=CONTROL!$B$18,CONTROL!$B$17,CONTROL!$B$17*(CONTROL!$B$18/F53)^CONTROL!$B$19)+E53*IF(G53<=CONTROL!$B$18,CONTROL!$B$17,CONTROL!$B$17*(CONTROL!$B$18/G53)^CONTROL!$B$19)-CONTROL!$B$20*IF(CONTROL!$B$20<=CONTROL!$B$18,CONTROL!$B$17,CONTROL!$B$17*(CONTROL!$B$18/CONTROL!$B$20)^CONTROL!$B$19)) | I53: =H53*CONTROL!$B$21 | J53: =I53*CONTROL!$B$34*DATA_SEGMENTS!$D$2/12-CONTROL!$B$37*CONTROL!$B$24*DATA_SEGMENTS!$F$2 | K53: =I53*CONTROL!$B$35*DATA_SEGMENTS!$D$3/12-CONTROL!$B$37*CONTROL!$B$24*DATA_SEGMENTS!$F$3 | L53: =I53*CONTROL!$B$36*DATA_SEGMENTS!$D$4/12-CONTROL!$B$37*CONTROL!$B$24*DATA_SEGMENTS!$F$4 | M53: =IF(B53<=DATA_SEGMENTS!$E$2,0,M52*DATA_SEGMENTS!$C$2+INDEX($J$46:$J$63,B53-DATA_SEGMENTS!$E$2)) | N53: =IF(B53<=DATA_SEGMENTS!$E$3,0,N52*DATA_SEGMENTS!$C$3+INDEX($K$46:$K$63,B53-DATA_SEGMENTS!$E$3)) | O53: =IF(B53<=DATA_SEGMENTS!$E$4,0,O52*DATA_SEGMENTS!$C$4+INDEX($L$46:$L$63,B53-DATA_SEGMENTS!$E$4)) | P53: =M53+N53+O53 | Q53: =C53+P53 | R53: =Q53*CONTROL!$B$12 | S53: =IF(B53>CONTROL!$B$30,CONTROL!$B$29,0) | T53: =-CONTROL!$B$37*CONTROL!$B$23 | U53: =(J53+K53+L53)*12*CONTROL!$B$22 | V53: =C53*CONTROL!$B$13+S53+T53+U53 | W53: =CONTROL!$B$14*(1+CONTROL!$B$16)^(B53/12) | X53: =CONTROL!$B$15*(1+CONTROL!$B$16)^(B53/12) | Y53: =R53+V53+W53+X53 | Z53: =Y53-Q53 | AA53: =AA52-Z53
A54: 2027-05 | B54: 9 | C54: =$C$41+$D$41*B54 | D54: =IF(B54-CONTROL!$B$30<=0,0,IF(B54-CONTROL!$B$30=1,CONTROL!$B$31,IF(B54-CONTROL!$B$30=2,CONTROL!$B$32,CONTROL!$B$33))) | E54: =CONTROL!$B$27*D54 | F54: =CONTROL!$B$20+E54*CONTROL!$B$28 | G54: =CONTROL!$B$20*CONTROL!$B$28+E54 | H54: =IF(E54<=0,0,CONTROL!$B$20*IF(F54<=CONTROL!$B$18,CONTROL!$B$17,CONTROL!$B$17*(CONTROL!$B$18/F54)^CONTROL!$B$19)+E54*IF(G54<=CONTROL!$B$18,CONTROL!$B$17,CONTROL!$B$17*(CONTROL!$B$18/G54)^CONTROL!$B$19)-CONTROL!$B$20*IF(CONTROL!$B$20<=CONTROL!$B$18,CONTROL!$B$17,CONTROL!$B$17*(CONTROL!$B$18/CONTROL!$B$20)^CONTROL!$B$19)) | I54: =H54*CONTROL!$B$21 | J54: =I54*CONTROL!$B$34*DATA_SEGMENTS!$D$2/12-CONTROL!$B$37*CONTROL!$B$24*DATA_SEGMENTS!$F$2 | K54: =I54*CONTROL!$B$35*DATA_SEGMENTS!$D$3/12-CONTROL!$B$37*CONTROL!$B$24*DATA_SEGMENTS!$F$3 | L54: =I54*CONTROL!$B$36*DATA_SEGMENTS!$D$4/12-CONTROL!$B$37*CONTROL!$B$24*DATA_SEGMENTS!$F$4 | M54: =IF(B54<=DATA_SEGMENTS!$E$2,0,M53*DATA_SEGMENTS!$C$2+INDEX($J$46:$J$63,B54-DATA_SEGMENTS!$E$2)) | N54: =IF(B54<=DATA_SEGMENTS!$E$3,0,N53*DATA_SEGMENTS!$C$3+INDEX($K$46:$K$63,B54-DATA_SEGMENTS!$E$3)) | O54: =IF(B54<=DATA_SEGMENTS!$E$4,0,O53*DATA_SEGMENTS!$C$4+INDEX($L$46:$L$63,B54-DATA_SEGMENTS!$E$4)) | P54: =M54+N54+O54 | Q54: =C54+P54 | R54: =Q54*CONTROL!$B$12 | S54: =IF(B54>CONTROL!$B$30,CONTROL!$B$29,0) | T54: =-CONTROL!$B$37*CONTROL!$B$23 | U54: =(J54+K54+L54)*12*CONTROL!$B$22 | V54: =C54*CONTROL!$B$13+S54+T54+U54 | W54: =CONTROL!$B$14*(1+CONTROL!$B$16)^(B54/12) | X54: =CONTROL!$B$15*(1+CONTROL!$B$16)^(B54/12) | Y54: =R54+V54+W54+X54 | Z54: =Y54-Q54 | AA54: =AA53-Z54
A55: 2027-06 | B55: 10 | C55: =$C$41+$D$41*B55 | D55: =IF(B55-CONTROL!$B$30<=0,0,IF(B55-CONTROL!$B$30=1,CONTROL!$B$31,IF(B55-CONTROL!$B$30=2,CONTROL!$B$32,CONTROL!$B$33))) | E55: =CONTROL!$B$27*D55 | F55: =CONTROL!$B$20+E55*CONTROL!$B$28 | G55: =CONTROL!$B$20*CONTROL!$B$28+E55 | H55: =IF(E55<=0,0,CONTROL!$B$20*IF(F55<=CONTROL!$B$18,CONTROL!$B$17,CONTROL!$B$17*(CONTROL!$B$18/F55)^CONTROL!$B$19)+E55*IF(G55<=CONTROL!$B$18,CONTROL!$B$17,CONTROL!$B$17*(CONTROL!$B$18/G55)^CONTROL!$B$19)-CONTROL!$B$20*IF(CONTROL!$B$20<=CONTROL!$B$18,CONTROL!$B$17,CONTROL!$B$17*(CONTROL!$B$18/CONTROL!$B$20)^CONTROL!$B$19)) | I55: =H55*CONTROL!$B$21 | J55: =I55*CONTROL!$B$34*DATA_SEGMENTS!$D$2/12-CONTROL!$B$37*CONTROL!$B$24*DATA_SEGMENTS!$F$2 | K55: =I55*CONTROL!$B$35*DATA_SEGMENTS!$D$3/12-CONTROL!$B$37*CONTROL!$B$24*DATA_SEGMENTS!$F$3 | L55: =I55*CONTROL!$B$36*DATA_SEGMENTS!$D$4/12-CONTROL!$B$37*CONTROL!$B$24*DATA_SEGMENTS!$F$4 | M55: =IF(B55<=DATA_SEGMENTS!$E$2,0,M54*DATA_SEGMENTS!$C$2+INDEX($J$46:$J$63,B55-DATA_SEGMENTS!$E$2)) | N55: =IF(B55<=DATA_SEGMENTS!$E$3,0,N54*DATA_SEGMENTS!$C$3+INDEX($K$46:$K$63,B55-DATA_SEGMENTS!$E$3)) | O55: =IF(B55<=DATA_SEGMENTS!$E$4,0,O54*DATA_SEGMENTS!$C$4+INDEX($L$46:$L$63,B55-DATA_SEGMENTS!$E$4)) | P55: =M55+N55+O55 | Q55: =C55+P55 | R55: =Q55*CONTROL!$B$12 | S55: =IF(B55>CONTROL!$B$30,CONTROL!$B$29,0) | T55: =-CONTROL!$B$37*CONTROL!$B$23 | U55: =(J55+K55+L55)*12*CONTROL!$B$22 | V55: =C55*CONTROL!$B$13+S55+T55+U55 | W55: =CONTROL!$B$14*(1+CONTROL!$B$16)^(B55/12) | X55: =CONTROL!$B$15*(1+CONTROL!$B$16)^(B55/12) | Y55: =R55+V55+W55+X55 | Z55: =Y55-Q55 | AA55: =AA54-Z55
A56: 2027-07 | B56: 11 | C56: =$C$41+$D$41*B56 | D56: =IF(B56-CONTROL!$B$30<=0,0,IF(B56-CONTROL!$B$30=1,CONTROL!$B$31,IF(B56-CONTROL!$B$30=2,CONTROL!$B$32,CONTROL!$B$33))) | E56: =CONTROL!$B$27*D56 | F56: =CONTROL!$B$20+E56*CONTROL!$B$28 | G56: =CONTROL!$B$20*CONTROL!$B$28+E56 | H56: =IF(E56<=0,0,CONTROL!$B$20*IF(F56<=CONTROL!$B$18,CONTROL!$B$17,CONTROL!$B$17*(CONTROL!$B$18/F56)^CONTROL!$B$19)+E56*IF(G56<=CONTROL!$B$18,CONTROL!$B$17,CONTROL!$B$17*(CONTROL!$B$18/G56)^CONTROL!$B$19)-CONTROL!$B$20*IF(CONTROL!$B$20<=CONTROL!$B$18,CONTROL!$B$17,CONTROL!$B$17*(CONTROL!$B$18/CONTROL!$B$20)^CONTROL!$B$19)) | I56: =H56*CONTROL!$B$21 | J56: =I56*CONTROL!$B$34*DATA_SEGMENTS!$D$2/12-CONTROL!$B$37*CONTROL!$B$24*DATA_SEGMENTS!$F$2 | K56: =I56*CONTROL!$B$35*DATA_SEGMENTS!$D$3/12-CONTROL!$B$37*CONTROL!$B$24*DATA_SEGMENTS!$F$3 | L56: =I56*CONTROL!$B$36*DATA_SEGMENTS!$D$4/12-CONTROL!$B$37*CONTROL!$B$24*DATA_SEGMENTS!$F$4 | M56: =IF(B56<=DATA_SEGMENTS!$E$2,0,M55*DATA_SEGMENTS!$C$2+INDEX($J$46:$J$63,B56-DATA_SEGMENTS!$E$2)) | N56: =IF(B56<=DATA_SEGMENTS!$E$3,0,N55*DATA_SEGMENTS!$C$3+INDEX($K$46:$K$63,B56-DATA_SEGMENTS!$E$3)) | O56: =IF(B56<=DATA_SEGMENTS!$E$4,0,O55*DATA_SEGMENTS!$C$4+INDEX($L$46:$L$63,B56-DATA_SEGMENTS!$E$4)) | P56: =M56+N56+O56 | Q56: =C56+P56 | R56: =Q56*CONTROL!$B$12 | S56: =IF(B56>CONTROL!$B$30,CONTROL!$B$29,0) | T56: =-CONTROL!$B$37*CONTROL!$B$23 | U56: =(J56+K56+L56)*12*CONTROL!$B$22 | V56: =C56*CONTROL!$B$13+S56+T56+U56 | W56: =CONTROL!$B$14*(1+CONTROL!$B$16)^(B56/12) | X56: =CONTROL!$B$15*(1+CONTROL!$B$16)^(B56/12) | Y56: =R56+V56+W56+X56 | Z56: =Y56-Q56 | AA56: =AA55-Z56
A57: 2027-08 | B57: 12 | C57: =$C$41+$D$41*B57 | D57: =IF(B57-CONTROL!$B$30<=0,0,IF(B57-CONTROL!$B$30=1,CONTROL!$B$31,IF(B57-CONTROL!$B$30=2,CONTROL!$B$32,CONTROL!$B$33))) | E57: =CONTROL!$B$27*D57 | F57: =CONTROL!$B$20+E57*CONTROL!$B$28 | G57: =CONTROL!$B$20*CONTROL!$B$28+E57 | H57: =IF(E57<=0,0,CONTROL!$B$20*IF(F57<=CONTROL!$B$18,CONTROL!$B$17,CONTROL!$B$17*(CONTROL!$B$18/F57)^CONTROL!$B$19)+E57*IF(G57<=CONTROL!$B$18,CONTROL!$B$17,CONTROL!$B$17*(CONTROL!$B$18/G57)^CONTROL!$B$19)-CONTROL!$B$20*IF(CONTROL!$B$20<=CONTROL!$B$18,CONTROL!$B$17,CONTROL!$B$17*(CONTROL!$B$18/CONTROL!$B$20)^CONTROL!$B$19)) | I57: =H57*CONTROL!$B$21 | J57: =I57*CONTROL!$B$34*DATA_SEGMENTS!$D$2/12-CONTROL!$B$37*CONTROL!$B$24*DATA_SEGMENTS!$F$2 | K57: =I57*CONTROL!$B$35*DATA_SEGMENTS!$D$3/12-CONTROL!$B$37*CONTROL!$B$24*DATA_SEGMENTS!$F$3 | L57: =I57*CONTROL!$B$36*DATA_SEGMENTS!$D$4/12-CONTROL!$B$37*CONTROL!$B$24*DATA_SEGMENTS!$F$4 | M57: =IF(B57<=DATA_SEGMENTS!$E$2,0,M56*DATA_SEGMENTS!$C$2+INDEX($J$46:$J$63,B57-DATA_SEGMENTS!$E$2)) | N57: =IF(B57<=DATA_SEGMENTS!$E$3,0,N56*DATA_SEGMENTS!$C$3+INDEX($K$46:$K$63,B57-DATA_SEGMENTS!$E$3)) | O57: =IF(B57<=DATA_SEGMENTS!$E$4,0,O56*DATA_SEGMENTS!$C$4+INDEX($L$46:$L$63,B57-DATA_SEGMENTS!$E$4)) | P57: =M57+N57+O57 | Q57: =C57+P57 | R57: =Q57*CONTROL!$B$12 | S57: =IF(B57>CONTROL!$B$30,CONTROL!$B$29,0) | T57: =-CONTROL!$B$37*CONTROL!$B$23 | U57: =(J57+K57+L57)*12*CONTROL!$B$22 | V57: =C57*CONTROL!$B$13+S57+T57+U57 | W57: =CONTROL!$B$14*(1+CONTROL!$B$16)^(B57/12) | X57: =CONTROL!$B$15*(1+CONTROL!$B$16)^(B57/12) | Y57: =R57+V57+W57+X57 | Z57: =Y57-Q57 | AA57: =AA56-Z57
... A63: 2028-02 | B63: 18 | C63: =$C$41+$D$41*B63 | D63: =IF(B63-CONTROL!$B$30<=0,0,IF(B63-CONTROL!$B$30=1,CONTROL!$B$31,IF(B63-CONTROL!$B$30=2,CONTROL!$B$32,CONTROL!$B$33))) | E63: =CONTROL!$B$27*D63 | F63: =CONTROL!$B$20+E63*CONTROL!$B$28 | G63: =CONTROL!$B$20*CONTROL!$B$28+E63 | H63: =IF(E63<=0,0,CONTROL!$B$20*IF(F63<=CONTROL!$B$18,CONTROL!$B$17,CONTROL!$B$17*(CONTROL!$B$18/F63)^CONTROL!$B$19)+E63*IF(G63<=CONTROL!$B$18,CONTROL!$B$17,CONTROL!$B$17*(CONTROL!$B$18/G63)^CONTROL!$B$19)-CONTROL!$B$20*IF(CONTROL!$B$20<=CONTROL!$B$18,CONTROL!$B$17,CONTROL!$B$17*(CONTROL!$B$18/CONTROL!$B$20)^CONTROL!$B$19)) | I63: =H63*CONTROL!$B$21 | J63: =I63*CONTROL!$B$34*DATA_SEGMENTS!$D$2/12-CONTROL!$B$37*CONTROL!$B$24*DATA_SEGMENTS!$F$2 | K63: =I63*CONTROL!$B$35*DATA_SEGMENTS!$D$3/12-CONTROL!$B$37*CONTROL!$B$24*DATA_SEGMENTS!$F$3 | L63: =I63*CONTROL!$B$36*DATA_SEGMENTS!$D$4/12-CONTROL!$B$37*CONTROL!$B$24*DATA_SEGMENTS!$F$4 | M63: =IF(B63<=DATA_SEGMENTS!$E$2,0,M62*DATA_SEGMENTS!$C$2+INDEX($J$46:$J$63,B63-DATA_SEGMENTS!$E$2)) | N63: =IF(B63<=DATA_SEGMENTS!$E$3,0,N62*DATA_SEGMENTS!$C$3+INDEX($K$46:$K$63,B63-DATA_SEGMENTS!$E$3)) | O63: =IF(B63<=DATA_SEGMENTS!$E$4,0,O62*DATA_SEGMENTS!$C$4+INDEX($L$46:$L$63,B63-DATA_SEGMENTS!$E$4)) | P63: =M63+N63+O63 | Q63: =C63+P63 | R63: =Q63*CONTROL!$B$12 | S63: =IF(B63>CONTROL!$B$30,CONTROL!$B$29,0) | T63: =-CONTROL!$B$37*CONTROL!$B$23 | U63: =(J63+K63+L63)*12*CONTROL!$B$22 | V63: =C63*CONTROL!$B$13+S63+T63+U63 | W63: =CONTROL!$B$14*(1+CONTROL!$B$16)^(B63/12) | X63: =CONTROL!$B$15*(1+CONTROL!$B$16)^(B63/12) | Y63: =R63+V63+W63+X63 | Z63: =Y63-Q63 | AA63: =AA62-Z63

Sheet OUT_SUMMARY
A1: NORTHWIND CLOUD — THE ANSWER
A2: ="Active scenario: "&CONTROL!$B$3
A4: POSITION TODAY
A5: ARR (latest actual month) | B5: =DATA_ACTUALS!C37*12
A6: Net burn, trailing 3 months | B6: =AVERAGE(DATA_ACTUALS!P35:P37)
A7: Cash on hand | B7: =CONTROL!$B$7
A8: Static runway (cash / current burn), months | B8: =CONTROL!$B$7/AVERAGE(DATA_ACTUALS!P35:P37)
A10: UNDER THE ACTIVE SCENARIO (18 months out)
A11: Incremental S&M, $/month | B11: =CONTROL!$B$29
A12: Paid Social spend retired, $/month | B12: =CONTROL!$B$37*CONTROL!$B$23
A13: Net incremental cost, $/month | B13: =CONTROL!$B$29-CONTROL!$B$37*CONTROL!$B$23
A14: ARR at month 18 | B14: =CALC_FORECAST!Q63*12
A15: Incremental ARR vs base at month 18 | B15: =CALC_FORECAST!P63*12
A16: Net burn at month 18 | B16: =CALC_FORECAST!Z63
A17: Cash at month 18 | B17: =CALC_FORECAST!AA63
A18: Months of cash left at month 18 | B18: =IFERROR(CALC_FORECAST!AA63/AVERAGE(CALC_FORECAST!Z61:Z63),"n/a")
A19: Incremental wins per month (fully ramped) | B19: =CALC_FORECAST!I63
A20: Incremental CAC | B20: =IFERROR(CONTROL!$B$29/CALC_FORECAST!I63,"n/a")
A21: Blended ACV of incremental wins | B21: =CONTROL!$B$34*DATA_SEGMENTS!$D$2+CONTROL!$B$35*DATA_SEGMENTS!$D$3+CONTROL!$B$36*DATA_SEGMENTS!$D$4
A22: Blended gross margin of incremental wins | B22: =CONTROL!$B$34*DATA_SEGMENTS!$B$2+CONTROL!$B$35*DATA_SEGMENTS!$B$3+CONTROL!$B$36*DATA_SEGMENTS!$B$4
A23: Incremental CAC payback (months) | B23: =IFERROR(B20/(B21/12*B22),"n/a")
A24: VERDICT vs the payback hurdle | B24: =IF(B23<=CONTROL!$B$9,"APPROVE","REJECT") | C24: ="payback "&TEXT(B23,"0.0")&" months vs hurdle "&TEXT(CONTROL!$B$9,"0")

Sheet DATA_SQL_CHECK
A1: metric_key | B1: reference_value | C1: tolerance | D1: source
A2: arr_latest | B2: 12374314 | C2: 0.005 | D2: SQL v_pnl_month, full precision
A3: burn_3m_avg | B3: 335925.36 | C3: 0.005 | D3: SQL v_pnl_month, full precision
A4: arr_bridge_closing_latest | B4: 12374314 | C4: 0.005 | D4: SQL Q02 (rounded 2dp -> tolerance 0.005)
A5: arr_bridge_max_residual | B5: 0 | C5: 0.005 | D5: SQL Q02
A6: cac__partner | B6: 29880 | C6: 0.5 | D6: SQL Q07 (rounded 0dp -> tolerance 0.5)
A7: payback__partner | B7: 12.5 | C7: 0.05 | D7: SQL Q07 (rounded 1dp -> tolerance 0.05)
A8: ltvcac__partner | B8: 5.25 | C8: 0.0051 | D8: SQL Q07 (rounded 2dp -> tolerance 0.005)
A9: cac__inbound_content | B9: 32118 | C9: 0.5 | D9: SQL Q07 (rounded 0dp -> tolerance 0.5)
A10: payback__inbound_content | B10: 18.8 | C10: 0.05 | D10: SQL Q07 (rounded 1dp -> tolerance 0.05)
A11: ltvcac__inbound_content | B11: 3.77 | C11: 0.0051 | D11: SQL Q07 (rounded 2dp -> tolerance 0.005)
A12: cac__paid_search | B12: 21277 | C12: 0.5 | D12: SQL Q07 (rounded 0dp -> tolerance 0.5)
A13: payback__paid_search | B13: 21.7 | C13: 0.05 | D13: SQL Q07 (rounded 1dp -> tolerance 0.05)
... A36: inc_payback__selective | B36: 11.2 | C36: 0.05 | D36: Python sensitivity src/04 (rounded 1dp)

Sheet CHECKS
A1: EXCEL vs SQL RECONCILIATION
A2: Excel value is computed by formula on this workbook. Reference value comes from the SQL warehouse or the Python cash model. Scenario-specific rows follow CONTROL!B3.
A4: check | B4: excel value | C4: reference value | D4: difference | E4: tolerance | F4: status | G4: note
A5: ARR, latest actual month | B5: =DATA_ACTUALS!C37*12 | C5: =IFERROR(INDEX(DATA_SQL_CHECK!$B$2:$B$36,MATCH("arr_latest",DATA_SQL_CHECK!$A$2:$A$36,0)),"key missing") | D5: =IFERROR(B5-C5,"n/a") | E5: =IFERROR(INDEX(DATA_SQL_CHECK!$C$2:$C$36,MATCH("arr_latest",DATA_SQL_CHECK!$A$2:$A$36,0)),"") | F5: =IF(AND(ISNUMBER(B5),ISNUMBER(C5)),IF(ABS(B5-C5)<=E5,"PASS","FAIL"),"FAIL") | G5: Sum of the fact table x 12
A6: Net burn, trailing 3 months | B6: =AVERAGE(DATA_ACTUALS!P35:P37) | C6: =IFERROR(INDEX(DATA_SQL_CHECK!$B$2:$B$36,MATCH("burn_3m_avg",DATA_SQL_CHECK!$A$2:$A$36,0)),"key missing") | D6: =IFERROR(B6-C6,"n/a") | E6: =IFERROR(INDEX(DATA_SQL_CHECK!$C$2:$C$36,MATCH("burn_3m_avg",DATA_SQL_CHECK!$A$2:$A$36,0)),"") | F6: =IF(AND(ISNUMBER(B6),ISNUMBER(C6)),IF(ABS(B6-C6)<=E6,"PASS","FAIL"),"FAIL") | G6: Excel averages the actuals
A7: ARR bridge, closing (latest month) | B7: =(DATA_ACTUALS!C36+DATA_ACTUALS!E37+DATA_ACTUALS!F37+DATA_ACTUALS!G37+DATA_ACTUALS!H37-DATA_ACTUALS!I37-DATA_ACTUALS!J37)*12 | C7: =IFERROR(INDEX(DATA_SQL_CHECK!$B$2:$B$36,MATCH("arr_bridge_closing_latest",DATA_SQL_CHECK!$A$2:$A$36,0)),"key missing") | D7: =IFERROR(B7-C7,"n/a") | E7: =IFERROR(INDEX(DATA_SQL_CHECK!$C$2:$C$36,MATCH("arr_bridge_closing_latest",DATA_SQL_CHECK!$A$2:$A$36,0)),"") | F7: =IF(AND(ISNUMBER(B7),ISNUMBER(C7)),IF(ABS(B7-C7)<=E7,"PASS","FAIL"),"FAIL") | G7: Excel rebuilds opening + movements and must land on closing
A8: CAC — channel row 1 | B8: =CALC_UNIT_ECON!E5 | C8: =IFERROR(INDEX(DATA_SQL_CHECK!$B$2:$B$36,MATCH("cac__"&DATA_CHANNELS!A2,DATA_SQL_CHECK!$A$2:$A$36,0)),"key missing") | D8: =IFERROR(B8-C8,"n/a") | E8: =IFERROR(INDEX(DATA_SQL_CHECK!$C$2:$C$36,MATCH("cac__"&DATA_CHANNELS!A2,DATA_SQL_CHECK!$A$2:$A$36,0)),"") | F8: =IF(AND(ISNUMBER(B8),ISNUMBER(C8)),IF(ABS(B8-C8)<=E8,"PASS","FAIL"),"FAIL") | G8: Formula from the cost pools
A9: CAC payback — channel row 1 | B9: =CALC_UNIT_ECON!G5 | C9: =IFERROR(INDEX(DATA_SQL_CHECK!$B$2:$B$36,MATCH("payback__"&DATA_CHANNELS!A2,DATA_SQL_CHECK!$A$2:$A$36,0)),"key missing") | D9: =IFERROR(B9-C9,"n/a") | E9: =IFERROR(INDEX(DATA_SQL_CHECK!$C$2:$C$36,MATCH("payback__"&DATA_CHANNELS!A2,DATA_SQL_CHECK!$A$2:$A$36,0)),"") | F9: =IF(AND(ISNUMBER(B9),ISNUMBER(C9)),IF(ABS(B9-C9)<=E9,"PASS","FAIL"),"FAIL") | G9: CAC / monthly gross profit
A10: LTV/CAC — channel row 1 | B10: =CALC_UNIT_ECON!I5 | C10: =IFERROR(INDEX(DATA_SQL_CHECK!$B$2:$B$36,MATCH("ltvcac__"&DATA_CHANNELS!A2,DATA_SQL_CHECK!$A$2:$A$36,0)),"key missing") | D10: =IFERROR(B10-C10,"n/a") | E10: =IFERROR(INDEX(DATA_SQL_CHECK!$C$2:$C$36,MATCH("ltvcac__"&DATA_CHANNELS!A2,DATA_SQL_CHECK!$A$2:$A$36,0)),"") | F10: =IF(AND(ISNUMBER(B10),ISNUMBER(C10)),IF(ABS(B10-C10)<=E10,"PASS","FAIL"),"FAIL") | G10: 60-month NRR-based LTV
A11: CAC — channel row 2 | B11: =CALC_UNIT_ECON!E6 | C11: =IFERROR(INDEX(DATA_SQL_CHECK!$B$2:$B$36,MATCH("cac__"&DATA_CHANNELS!A3,DATA_SQL_CHECK!$A$2:$A$36,0)),"key missing") | D11: =IFERROR(B11-C11,"n/a") | E11: =IFERROR(INDEX(DATA_SQL_CHECK!$C$2:$C$36,MATCH("cac__"&DATA_CHANNELS!A3,DATA_SQL_CHECK!$A$2:$A$36,0)),"") | F11: =IF(AND(ISNUMBER(B11),ISNUMBER(C11)),IF(ABS(B11-C11)<=E11,"PASS","FAIL"),"FAIL") | G11: Formula from the cost pools
A12: CAC payback — channel row 2 | B12: =CALC_UNIT_ECON!G6 | C12: =IFERROR(INDEX(DATA_SQL_CHECK!$B$2:$B$36,MATCH("payback__"&DATA_CHANNELS!A3,DATA_SQL_CHECK!$A$2:$A$36,0)),"key missing") | D12: =IFERROR(B12-C12,"n/a") | E12: =IFERROR(INDEX(DATA_SQL_CHECK!$C$2:$C$36,MATCH("payback__"&DATA_CHANNELS!A3,DATA_SQL_CHECK!$A$2:$A$36,0)),"") | F12: =IF(AND(ISNUMBER(B12),ISNUMBER(C12)),IF(ABS(B12-C12)<=E12,"PASS","FAIL"),"FAIL") | G12: CAC / monthly gross profit
A13: LTV/CAC — channel row 2 | B13: =CALC_UNIT_ECON!I6 | C13: =IFERROR(INDEX(DATA_SQL_CHECK!$B$2:$B$36,MATCH("ltvcac__"&DATA_CHANNELS!A3,DATA_SQL_CHECK!$A$2:$A$36,0)),"key missing") | D13: =IFERROR(B13-C13,"n/a") | E13: =IFERROR(INDEX(DATA_SQL_CHECK!$C$2:$C$36,MATCH("ltvcac__"&DATA_CHANNELS!A3,DATA_SQL_CHECK!$A$2:$A$36,0)),"") | F13: =IF(AND(ISNUMBER(B13),ISNUMBER(C13)),IF(ABS(B13-C13)<=E13,"PASS","FAIL"),"FAIL") | G13: 60-month NRR-based LTV
A14: CAC — channel row 3 | B14: =CALC_UNIT_ECON!E7 | C14: =IFERROR(INDEX(DATA_SQL_CHECK!$B$2:$B$36,MATCH("cac__"&DATA_CHANNELS!A4,DATA_SQL_CHECK!$A$2:$A$36,0)),"key missing") | D14: =IFERROR(B14-C14,"n/a") | E14: =IFERROR(INDEX(DATA_SQL_CHECK!$C$2:$C$36,MATCH("cac__"&DATA_CHANNELS!A4,DATA_SQL_CHECK!$A$2:$A$36,0)),"") | F14: =IF(AND(ISNUMBER(B14),ISNUMBER(C14)),IF(ABS(B14-C14)<=E14,"PASS","FAIL"),"FAIL") | G14: Formula from the cost pools
A15: CAC payback — channel row 3 | B15: =CALC_UNIT_ECON!G7 | C15: =IFERROR(INDEX(DATA_SQL_CHECK!$B$2:$B$36,MATCH("payback__"&DATA_CHANNELS!A4,DATA_SQL_CHECK!$A$2:$A$36,0)),"key missing") | D15: =IFERROR(B15-C15,"n/a") | E15: =IFERROR(INDEX(DATA_SQL_CHECK!$C$2:$C$36,MATCH("payback__"&DATA_CHANNELS!A4,DATA_SQL_CHECK!$A$2:$A$36,0)),"") | F15: =IF(AND(ISNUMBER(B15),ISNUMBER(C15)),IF(ABS(B15-C15)<=E15,"PASS","FAIL"),"FAIL") | G15: CAC / monthly gross profit
A16: LTV/CAC — channel row 3 | B16: =CALC_UNIT_ECON!I7 | C16: =IFERROR(INDEX(DATA_SQL_CHECK!$B$2:$B$36,MATCH("ltvcac__"&DATA_CHANNELS!A4,DATA_SQL_CHECK!$A$2:$A$36,0)),"key missing") | D16: =IFERROR(B16-C16,"n/a") | E16: =IFERROR(INDEX(DATA_SQL_CHECK!$C$2:$C$36,MATCH("ltvcac__"&DATA_CHANNELS!A4,DATA_SQL_CHECK!$A$2:$A$36,0)),"") | F16: =IF(AND(ISNUMBER(B16),ISNUMBER(C16)),IF(ABS(B16-C16)<=E16,"PASS","FAIL"),"FAIL") | G16: 60-month NRR-based LTV
A17: CAC — channel row 4 | B17: =CALC_UNIT_ECON!E8 | C17: =IFERROR(INDEX(DATA_SQL_CHECK!$B$2:$B$36,MATCH("cac__"&DATA_CHANNELS!A5,DATA_SQL_CHECK!$A$2:$A$36,0)),"key missing") | D17: =IFERROR(B17-C17,"n/a") | E17: =IFERROR(INDEX(DATA_SQL_CHECK!$C$2:$C$36,MATCH("cac__"&DATA_CHANNELS!A5,DATA_SQL_CHECK!$A$2:$A$36,0)),"") | F17: =IF(AND(ISNUMBER(B17),ISNUMBER(C17)),IF(ABS(B17-C17)<=E17,"PASS","FAIL"),"FAIL") | G17: Formula from the cost pools
A18: CAC payback — channel row 4 | B18: =CALC_UNIT_ECON!G8 | C18: =IFERROR(INDEX(DATA_SQL_CHECK!$B$2:$B$36,MATCH("payback__"&DATA_CHANNELS!A5,DATA_SQL_CHECK!$A$2:$A$36,0)),"key missing") | D18: =IFERROR(B18-C18,"n/a") | E18: =IFERROR(INDEX(DATA_SQL_CHECK!$C$2:$C$36,MATCH("payback__"&DATA_CHANNELS!A5,DATA_SQL_CHECK!$A$2:$A$36,0)),"") | F18: =IF(AND(ISNUMBER(B18),ISNUMBER(C18)),IF(ABS(B18-C18)<=E18,"PASS","FAIL"),"FAIL") | G18: CAC / monthly gross profit
A19: LTV/CAC — channel row 4 | B19: =CALC_UNIT_ECON!I8 | C19: =IFERROR(INDEX(DATA_SQL_CHECK!$B$2:$B$36,MATCH("ltvcac__"&DATA_CHANNELS!A5,DATA_SQL_CHECK!$A$2:$A$36,0)),"key missing") | D19: =IFERROR(B19-C19,"n/a") | E19: =IFERROR(INDEX(DATA_SQL_CHECK!$C$2:$C$36,MATCH("ltvcac__"&DATA_CHANNELS!A5,DATA_SQL_CHECK!$A$2:$A$36,0)),"") | F19: =IF(AND(ISNUMBER(B19),ISNUMBER(C19)),IF(ABS(B19-C19)<=E19,"PASS","FAIL"),"FAIL") | G19: 60-month NRR-based LTV
A20: CAC — channel row 5 | B20: =CALC_UNIT_ECON!E9 | C20: =IFERROR(INDEX(DATA_SQL_CHECK!$B$2:$B$36,MATCH("cac__"&DATA_CHANNELS!A6,DATA_SQL_CHECK!$A$2:$A$36,0)),"key missing") | D20: =IFERROR(B20-C20,"n/a") | E20: =IFERROR(INDEX(DATA_SQL_CHECK!$C$2:$C$36,MATCH("cac__"&DATA_CHANNELS!A6,DATA_SQL_CHECK!$A$2:$A$36,0)),"") | F20: =IF(AND(ISNUMBER(B20),ISNUMBER(C20)),IF(ABS(B20-C20)<=E20,"PASS","FAIL"),"FAIL") | G20: Formula from the cost pools
A21: CAC payback — channel row 5 | B21: =CALC_UNIT_ECON!G9 | C21: =IFERROR(INDEX(DATA_SQL_CHECK!$B$2:$B$36,MATCH("payback__"&DATA_CHANNELS!A6,DATA_SQL_CHECK!$A$2:$A$36,0)),"key missing") | D21: =IFERROR(B21-C21,"n/a") | E21: =IFERROR(INDEX(DATA_SQL_CHECK!$C$2:$C$36,MATCH("payback__"&DATA_CHANNELS!A6,DATA_SQL_CHECK!$A$2:$A$36,0)),"") | F21: =IF(AND(ISNUMBER(B21),ISNUMBER(C21)),IF(ABS(B21-C21)<=E21,"PASS","FAIL"),"FAIL") | G21: CAC / monthly gross profit
A22: LTV/CAC — channel row 5 | B22: =CALC_UNIT_ECON!I9 | C22: =IFERROR(INDEX(DATA_SQL_CHECK!$B$2:$B$36,MATCH("ltvcac__"&DATA_CHANNELS!A6,DATA_SQL_CHECK!$A$2:$A$36,0)),"key missing") | D22: =IFERROR(B22-C22,"n/a") | E22: =IFERROR(INDEX(DATA_SQL_CHECK!$C$2:$C$36,MATCH("ltvcac__"&DATA_CHANNELS!A6,DATA_SQL_CHECK!$A$2:$A$36,0)),"") | F22: =IF(AND(ISNUMBER(B22),ISNUMBER(C22)),IF(ABS(B22-C22)<=E22,"PASS","FAIL"),"FAIL") | G22: 60-month NRR-based LTV
A23: CAC — channel row 6 | B23: =CALC_UNIT_ECON!E10 | C23: =IFERROR(INDEX(DATA_SQL_CHECK!$B$2:$B$36,MATCH("cac__"&DATA_CHANNELS!A7,DATA_SQL_CHECK!$A$2:$A$36,0)),"key missing") | D23: =IFERROR(B23-C23,"n/a") | E23: =IFERROR(INDEX(DATA_SQL_CHECK!$C$2:$C$36,MATCH("cac__"&DATA_CHANNELS!A7,DATA_SQL_CHECK!$A$2:$A$36,0)),"") | F23: =IF(AND(ISNUMBER(B23),ISNUMBER(C23)),IF(ABS(B23-C23)<=E23,"PASS","FAIL"),"FAIL") | G23: Formula from the cost pools
A24: CAC payback — channel row 6 | B24: =CALC_UNIT_ECON!G10 | C24: =IFERROR(INDEX(DATA_SQL_CHECK!$B$2:$B$36,MATCH("payback__"&DATA_CHANNELS!A7,DATA_SQL_CHECK!$A$2:$A$36,0)),"key missing") | D24: =IFERROR(B24-C24,"n/a") | E24: =IFERROR(INDEX(DATA_SQL_CHECK!$C$2:$C$36,MATCH("payback__"&DATA_CHANNELS!A7,DATA_SQL_CHECK!$A$2:$A$36,0)),"") | F24: =IF(AND(ISNUMBER(B24),ISNUMBER(C24)),IF(ABS(B24-C24)<=E24,"PASS","FAIL"),"FAIL") | G24: CAC / monthly gross profit
A25: LTV/CAC — channel row 6 | B25: =CALC_UNIT_ECON!I10 | C25: =IFERROR(INDEX(DATA_SQL_CHECK!$B$2:$B$36,MATCH("ltvcac__"&DATA_CHANNELS!A7,DATA_SQL_CHECK!$A$2:$A$36,0)),"key missing") | D25: =IFERROR(B25-C25,"n/a") | E25: =IFERROR(INDEX(DATA_SQL_CHECK!$C$2:$C$36,MATCH("ltvcac__"&DATA_CHANNELS!A7,DATA_SQL_CHECK!$A$2:$A$36,0)),"") | F25: =IF(AND(ISNUMBER(B25),ISNUMBER(C25)),IF(ABS(B25-C25)<=E25,"PASS","FAIL"),"FAIL") | G25: 60-month NRR-based LTV
A26: Cash at month 18 (active scenario) | B26: =CALC_FORECAST!AA63 | C26: =IFERROR(INDEX(DATA_SQL_CHECK!$B$2:$B$36,MATCH("cash_m18__"&CONTROL!$B$3,DATA_SQL_CHECK!$A$2:$A$36,0)),"key missing") | D26: =IFERROR(B26-C26,"n/a") | E26: =IFERROR(INDEX(DATA_SQL_CHECK!$C$2:$C$36,MATCH("cash_m18__"&CONTROL!$B$3,DATA_SQL_CHECK!$A$2:$A$36,0)),"") | F26: =IF(AND(ISNUMBER(B26),ISNUMBER(C26)),IF(ABS(B26-C26)<=E26,"PASS","FAIL"),"FAIL") | G26: Follows the scenario switch
A27: ARR at month 18 (active scenario) | B27: =CALC_FORECAST!Q63*12 | C27: =IFERROR(INDEX(DATA_SQL_CHECK!$B$2:$B$36,MATCH("arr_m18__"&CONTROL!$B$3,DATA_SQL_CHECK!$A$2:$A$36,0)),"key missing") | D27: =IFERROR(B27-C27,"n/a") | E27: =IFERROR(INDEX(DATA_SQL_CHECK!$C$2:$C$36,MATCH("arr_m18__"&CONTROL!$B$3,DATA_SQL_CHECK!$A$2:$A$36,0)),"") | F27: =IF(AND(ISNUMBER(B27),ISNUMBER(C27)),IF(ABS(B27-C27)<=E27,"PASS","FAIL"),"FAIL") | G27: Follows the scenario switch
A28: Incremental ARR at month 18 (active) | B28: =CALC_FORECAST!P63*12 | C28: =IFERROR(INDEX(DATA_SQL_CHECK!$B$2:$B$36,MATCH("delta_arr_m18__"&CONTROL!$B$3,DATA_SQL_CHECK!$A$2:$A$36,0)),"key missing") | D28: =IFERROR(B28-C28,"n/a") | E28: =IFERROR(INDEX(DATA_SQL_CHECK!$C$2:$C$36,MATCH("delta_arr_m18__"&CONTROL!$B$3,DATA_SQL_CHECK!$A$2:$A$36,0)),"") | F28: =IF(AND(ISNUMBER(B28),ISNUMBER(C28)),IF(ABS(B28-C28)<=E28,"PASS","FAIL"),"FAIL") | G28: Follows the scenario switch
A30: OVERALL | B30: =COUNTIF(F5:F28,"PASS")&" / "&24&" PASS" | C30: =IF(COUNTIF(F5:F28,"FAIL")=0,"ALL CHECKS PASS",COUNTIF(F5:F28,"FAIL")&" FAILING")
